AUTHORS.txt
CHANGES.txt
MANIFEST.in
README.rst
development.ini
setup.cfg
setup.py
kotti_software/.coverage
kotti_software/__init__.py
kotti_software/resources.py
kotti_software/static.py
kotti_software/views.py
kotti_software.egg-info/PKG-INFO
kotti_software.egg-info/SOURCES.txt
kotti_software.egg-info/dependency_links.txt
kotti_software.egg-info/not-zip-safe
kotti_software.egg-info/requires.txt
kotti_software.egg-info/top_level.txt
kotti_software/locale/kotti_software.pot
kotti_software/locale/de/LC_MESSAGES/kotti_software.po
kotti_software/locale/en/LC_MESSAGES/kotti_software.po
kotti_software/static/kotti_software.js
kotti_software/static/kotti_software.min.js
kotti_software/static/loader.gif
kotti_software/static/style.css
kotti_software/templates/macros.pt
kotti_software/templates/softwarecollection-navpills-view.pt
kotti_software/templates/softwarecollection-view.pt
kotti_software/templates/softwareproject-view.pt