Metadata-Version: 1.0
Name: kotti-software
Version: 0.1.4
Summary: Kotti software -- adds a software project listing to your site
Home-page: http://github.com/geojeff/kotti_software
Author: Jeff Pittman
Author-email: geojeff@me.com
License:  BSD-derived (http://www.repoze.org/LICENSE.txt)
Keywords: kotti software
Platform: UNKNOWN
Classifier: Development Status :: 3 - Alpha
Classifier: Environment :: Web Environment
Classifier: Intended Audience :: Developers
Classifier: Operating System :: OS Independent
Classifier: Programming Language :: Python
Classifier: Framework :: Pyramid
